logger_manager/LoggerManager.py
logger_manager/__init__.py
pizza_logger_manager_g-1.0.0.dist-info/METADATA
pizza_logger_manager_g-1.0.0.dist-info/WHEEL
pizza_logger_manager_g-1.0.0.dist-info/top_level.txt
pizza_logger_manager_g-1.0.0.dist-info/RECORD
